gliese_plugin/__init__.py
gliese_plugin/hookspecs.py
gliese_plugin/host.py
gliese_plugin/lib.py
gliese_plugin-1.0.0.dist-info/METADATA
gliese_plugin-1.0.0.dist-info/WHEEL
gliese_plugin-1.0.0.dist-info/entry_points.txt
gliese_plugin-1.0.0.dist-info/top_level.txt
gliese_plugin-1.0.0.dist-info/RECORD
