Metadata-Version: 2.1
Name: gliese-plugin
Version: 1.0.0
Summary: UNKNOWN
Home-page: https://git.n.xiaomi.com/miphone-test-framework/gps-auto-test/gps-devices-resource
Author: Minghuan Ma
Author-email: maming3@xiaomi.com
License: UNKNOWN
Platform: UNKNOWN
Requires-Dist: pluggy (<1.0,>=0.3)
Requires-Dist: requests
Requires-Dist: transitions
Requires-Dist: geopy
